src/__init__.py
src/html_content.py
src/index.html
src/main.py
src/web_server.py
dbt_run_visualizer-0.1.0.dist-info/LICENSE
dbt_run_visualizer-0.1.0.dist-info/METADATA
dbt_run_visualizer-0.1.0.dist-info/WHEEL
dbt_run_visualizer-0.1.0.dist-info/entry_points.txt
dbt_run_visualizer-0.1.0.dist-info/top_level.txt
dbt_run_visualizer-0.1.0.dist-info/RECORD
